{
    "data": [
        {
            "id": "85gfsd1u",
            "title": "某交易员9天前用10倍杠杆做空4万枚ETH，目前浮盈超1215万美元",
            "description": "PANews 6月20日消息，据Lookonchain报道，交易员0xcB92在9天前用10倍杠杆做空4万枚ETH（价值1亿美元），目前未实现利润超过1215万美元，外加17.28万美元资金费率收入。",
            "link": "https://www.panewslab.com/zh/sqarticledetails/85gfsd1u.html",
            "pub_date": "2025-06-20 23:09:23",
            "source": "panewslab",
            "kind": 2,
            "language": "zh-CN"
        },
        {
            "id": "nsnzb4ll",
            "title": "美联储货币政策报告：通胀“略高”，就业市场“状况良好”",
            "description": "PANews 6月20日消息，据金十报道，美联储货币政策报告写道，通胀“略高”，就业市场“状况良好”。美元外汇价值普遍下跌。四月初国债市场运作仍然有序，但流动性下降至2023年初以来的水平。2025年开局发展缓慢与关税调整有关。关税对家庭和企业信心造成了影响，关税影响尚未在官方数据中体现，评估关税对经济影响仍为时过早。部分早期迹象显示关税推动了通胀上升。金融稳定在不确定性加剧中情况下“具有韧性”。",
            "link": "https://www.panewslab.com/zh/sqarticledetails/nsnzb4ll.html",
            "pub_date": "2025-06-20 23:02:56",
            "source": "panewslab",
            "kind": 2,
            "language": "zh-CN"
        },
        {
            "id": "hde9otuw",
            "title": "美联储货币政策报告：现在评估关税对经济的影响还为时过早",
            "description": "PANews 6月20日消息，据金十报道，美联储周五向国会发布的最新货币政策报告称，美国通胀率有所上升，劳动力市场状况稳健，但暗示特朗普的关税措施影响可能才刚刚开始显现，并重申了美联储的观点，即可以等待更明确的情况之后再采取行动。美联储在报告中称：“今年进口关税增加对美国消费者价格的影响是高度不确定的，因为贸易政策在继续演变，现在评估消费者和企业将如何反应还为时过早。尽管关税的影响无法从官方消费者价格统计数据中直接观察到，但今年各类商品的净价格变化模式表明，关税可能是近期商品通胀回升的原因之一。”报告还称，尽管存在不确定性，但金融体系一直具有“弹性”。",
            "link": "https://www.panewslab.com/zh/sqarticledetails/hde9otuw.html",
            "pub_date": "2025-06-20 23:05:10",
            "source": "panewslab",
            "kind": 2,
            "language": "zh-CN"
        },
        {
            "id": "oxnd55cl",
            "title": "BTC跌破104000美元，日内下跌 0.17%",
            "description": "PANews 6月20日消息，欧易OKX行情显示，BTC刚刚跌破104000美元，现报103929.70美元/枚，日内下跌 0.17%。",
            "link": "https://www.panewslab.com/zh/sqarticledetails/oxnd55cl.html",
            "pub_date": "2025-06-20 22:59:20",
            "source": "panewslab",
            "kind": 2,
            "language": "zh-CN"
        },
        {
            "id": "38efcams",
            "title": "俄罗斯要求以色列立即停止对伊朗的攻击和突袭",
            "description": "PANews 6月20日消息，据金十报道，俄罗斯驻联合国大使表示，以色列的行动有可能将第三国卷入冲突。俄罗斯要求以色列立即停止对伊朗的攻击和突袭。",
            "link": "https://www.panewslab.com/zh/sqarticledetails/38efcams.html",
            "pub_date": "2025-06-20 22:55:16",
            "source": "panewslab",
            "kind": 2,
            "language": "zh-CN"
        },
        {
            "id": "1lexa3v5",
            "title": "ETH跌破2500美元，日内涨幅 0.25%",
            "description": "PANews 6月20日消息，欧易OKX行情显示，ETH刚刚跌破2500美元，现报2499.20美元/枚，日内涨幅 0.25%。",
            "link": "https://www.panewslab.com/zh/sqarticledetails/1lexa3v5.html",
            "pub_date": "2025-06-20 22:51:10",
            "source": "panewslab",
            "kind": 2,
            "language": "zh-CN"
        },
        {
            "id": "620ssvrj",
            "title": "Trend Research疑似掌控着NEIRO（大写）代币总量的64.25%",
            "description": "PANews 6月20日消息，据链上分析师余烬监测，Trend Research除了持有着17.3万枚ETH，还掌控着Meme币 @NeiroOnEthereum(大写NEIRO，合约尾号2637) 64.25%总量的代币。",
            "link": "https://www.panewslab.com/zh/sqarticledetails/620ssvrj.html",
            "pub_date": "2025-06-20 22:44:11",
            "source": "panewslab",
            "kind": 2,
            "language": "zh-CN"
        },
        {
            "id": "o5s28x7h",
            "title": "前SpaceX高管创立的加密平台Stackup完成420万美元种子轮融资，1kx领投",
            "description": "PANews 6月20日消息，据Decrypt报道，前SpaceX任务经理John Rising创立的加密平台Stackup完成420万美元种子轮融资，由1kx领投，Y Combinator和Digital Currency Group等三家公司参投。该平台通过账户抽象技术为企业提供“对去中心化资产的集中控制”方案，支持支出限额、批量交易审核等功能。\r\nRising以航天工程经验强调系统安全性设计的重要性，指出当前加密领域过度关注安全防护而忽视操作安全。Stackup团队现由4人组成，其技术此前已应用于Coinbase和Trust Wallet的钱包开发。",
            "link": "https://www.panewslab.com/zh/sqarticledetails/o5s28x7h.html",
            "pub_date": "2025-06-20 22:05:19",
            "source": "panewslab",
            "kind": 2,
            "language": "zh-CN"
        },
        {
            "id": "kdm62c40",
            "title": "Kraken将总部从旧金山迁至怀俄明州",
            "description": "PANews 6月20日消息，据Crypto In America报道，美国加密交易所Kraken将总部从旧金山迁至怀俄明州夏延市。该决定基于怀俄明州在数字资产政策方面的领先地位，包括将数字资产定义为财产、保护私钥等明确立法。Kraken四年来已在该州投入30万美元支持怀俄明大学加密教育项目，并联合主办区块链研讨会。怀俄明州参议员Cynthia Lummis对此表示欢迎，指出该州近十年来始终走在数字资产政策前沿。尽管员工仍保持远程办公，此次搬迁标志着Kraken正式与这个拥有完善监管沙箱的司法管辖区建立更紧密联系。",
            "link": "https://www.panewslab.com/zh/sqarticledetails/kdm62c40.html",
            "pub_date": "2025-06-20 22:00:22",
            "source": "panewslab",
            "kind": 2,
            "language": "zh-CN"
        },
        {
            "id": "fcbnza8q",
            "title": "Coinbase获得欧盟加密牌照，并将欧盟总部从爱尔兰迁至卢森堡",
            "description": "PANews 6月20日消息，据CNBC报道，加密交易所Coinbase宣布获得卢森堡金融监管机构CSSF颁发的MiCA牌照，成为首家获欧盟全面授权的美国加密交易平台。该公司同时宣布将欧盟总部从爱尔兰迁至卢森堡，理由是后者更具前瞻性的金融政策环境。Coinbase首席执行官Brian Armstrong表示：“Coinbase全力投入欧洲市场，MiCA设定了标准，卢森堡凭借其亲商环境和审慎的监管方式，正引领行业发展。”",
            "link": "https://www.panewslab.com/zh/sqarticledetails/fcbnza8q.html",
            "pub_date": "2025-06-20 21:52:10",
            "source": "panewslab",
            "kind": 2,
            "language": "zh-CN"
        },
        {
            "id": "oy6ukcb1",
            "title": "“美联储传声筒”：美联储理事沃勒继续保持其最鸽派的立场",
            "description": "PANews 6月20日消息，据金十报道，“美联储传声筒”Nick Timiraos表示，美联储理事沃勒继续在美国联邦公开市场委员会（FOMC）的同事中保持最鸽派的立场。沃勒在不久前表示：“我完全赞成这样的说法，也许我们应该在下次会议上开始考虑削减政策利率，因为我们不想等到就业市场崩溃后才开始削减政策利率。”沃勒暗示了委员会内部的动态——根据当前的数据，FOMC内部并不支持在7月降息。这就引发了一个问题：他是否在为7月会议上“提出异议支持降息”做铺垫？在那些希望被提名为美联储主席的人中，沃勒或许是迄今为止提出降息理由最具理论深度的一位。",
            "link": "https://www.panewslab.com/zh/sqarticledetails/oy6ukcb1.html",
            "pub_date": "2025-06-20 21:46:50",
            "source": "panewslab",
            "kind": 2,
            "language": "zh-CN"
        },
        {
            "id": "gsyr5aie",
            "title": "知情人士：Pump.fun代币拍卖与上线再次延期",
            "description": "PANews 6月20日消息，据吴说获悉，原定于6月底举行的Pump.fun代币拍卖与上线活动再次延期，目前预计是7月中旬。知情人士透露，自去年年底Pump.fun计划发行并拍卖代币后，已经“无数次延期”。Pump.fun此次代币拍卖的估值为40亿美元。Pump.fun团队也在积极地向各种基金兜售代币额度。",
            "link": "https://www.panewslab.com/zh/sqarticledetails/gsyr5aie.html",
            "pub_date": "2025-06-20 21:39:41",
            "source": "panewslab",
            "kind": 2,
            "language": "zh-CN"
        },
        {
            "id": "mip2ypu8",
            "title": "KindlyMD与Nakamoto宣布新增5150万美元PIPE融资，以支持比特币储备计划",
            "description": "PANews 6月20日消息，据Businesswire报道，此前已宣布计划与比特币原生控股公司Nakamoto Holdings Inc.合并的Kindly MD, Inc.（纳斯达克代码：NAKA）宣布，其完成额外5150万美元的私募股权公开上市融资（“PIPE融资”），以支持其建立比特币储备的计划。截至目前，KindlyMD通过PIPE融资已筹集约5.63亿美元，若计入可转换债券，总计筹集约7.63亿美元。Nakamoto创始人兼首席执行官David Bailey表示，公司将继续执行战略，尽可能筹集更多资金，以买入尽可能多的比特币。PIPE融资的净收益将由KindlyMD用于购买比特币，以及用作运营资金和一般企业用途。",
            "link": "https://www.panewslab.com/zh/sqarticledetails/mip2ypu8.html",
            "pub_date": "2025-06-20 21:40:50",
            "source": "panewslab",
            "kind": 2,
            "language": "zh-CN"
        },
        {
            "id": "5lo104yv",
            "title": "以太坊开发人员再次敲定Fusaka升级范围，现涵盖12个EIP",
            "description": "PANews 6月20日消息，会议纪要显示，第214次以太坊执行层核心开发者会议 (ACDE) 重新审视了上一次会议中做出的决定，同意保持Fusaka升级的最终范围基本不变，仅添加一项额外的EIP，即EIP 7939。开发人员同意在Fusaka升级中包含以下12个EIP：EIP-7594 （PeerDAS-对等数据可用性采样）、EIP-7823（设置MODEXP的上限）、EIP-7825（交易Gas上限）、EIP-7883（ModExp Gas成本增加）、EIP-7892（仅限Blob参数的硬分叉）、EIP-7917（确定性提议者前瞻）、EIP-7918（Blob基础费用受执行成本限制）、EIP-7935（将默认gas限制设置为XX0M）、EIP-7951（secp256r1曲线支持的预编译）、EIP-7907（计量合约代码大小并增加限制）、EIP-7934（RLP执行区块大小限制）、[新] EIP-7939（用于计数前导零的新操作码）。\r\n开发者调整了部分EIP实施细节：将EIP-7907合约代码大小上限从256KB降至48KB；EIP-7918的blob基础费用参数从2^14调整为2^13；并将最大blob计数参数从EIP-7892移至EIP-7594。会议决定若满足至少3个共识层和3个执行层客户端团队就绪的条件，将于6月23日启动Fusaka Devnet 2测试网。开发者同时讨论了Glamsterdam升级的两个新提案，但因测试数据不足，部分参数调整将延至Devnet 3阶段实施。",
            "link": "https://www.panewslab.com/zh/sqarticledetails/5lo104yv.html",
            "pub_date": "2025-06-20 21:32:30",
            "source": "panewslab",
            "kind": 2,
            "language": "zh-CN"
        },
        {
            "id": "z7o8sbqj",
            "title": "Coinbase已向德国居民开放POPCAT和SQD代币交易",
            "description": "PANews 6月20日消息，Coinbase Assets在X平台宣布，Popcat(POPCAT)和Subsquid (SQD) 现已面向德国居民开放。",
            "link": "https://www.panewslab.com/zh/sqarticledetails/z7o8sbqj.html",
            "pub_date": "2025-06-20 21:16:07",
            "source": "panewslab",
            "kind": 2,
            "language": "zh-CN"
        },
        {
            "id": "ti677ky9",
            "title": "美联储理事沃勒发出明确鸽派信号：赞成在7月降息",
            "description": "PANews 6月20日消息，据金十报道，美联储理事沃勒最新表示，他赞成应该在7月份考虑降息的说法，认为关税不会导致持续通胀。他表示，关税将是一次性因素，美联储不应等到就业市场崩溃后才降息。沃勒称，当前，就业市场稳定，但开始出现一些迹象，比如应届毕业生失业率较高等。六个月以来，美联储一直在观望，等待通胀冲击的到来。沃勒认为，美联储有降低利率的空间，然后看看通胀会发生什么。沃勒表示，美联储最早可能在7月就具备降息的条件。在沃勒发表此番言论之前，市场押注美联储在7月降息的可能性只有14%。",
            "link": "https://www.panewslab.com/zh/sqarticledetails/ti677ky9.html",
            "pub_date": "2025-06-20 21:05:49",
            "source": "panewslab",
            "kind": 2,
            "language": "zh-CN"
        },
        {
            "id": "zmioiuwh",
            "title": "阿布扎比上市比特币矿企Phoenix Group考虑进军AI领域，并将部分业务转至美国",
            "description": "PANews 6月20日消息，据Semafor报道，在阿布扎比上市的比特币矿商Phoenix Group首席执行官Munaf Ali在接受采访时表示，该公司计划在未来两年内将其全球数据中心容量翻一番，达到1千兆瓦以上，以扩展到人工智能领域，并正在考虑将部分业务转移到美国。Ali指出：“比特币挖矿6个月即可投产，而AI数据中心需数年建设周期，两者结合可对冲风险。”\r\nPhoenix计划剥离其挖矿和数据中心业务，并在美国交易所上市，阿布扎比母公司将保留多数股权。Ali没有透露具体时间表，但表示双重上市将有助于获得资金，并受益于美国科技公司更高的估值。\r\n此前去年12月消息，Phoenix Group计划于2025年年在美双重上市。",
            "link": "https://www.panewslab.com/zh/sqarticledetails/zmioiuwh.html",
            "pub_date": "2025-06-20 20:28:05",
            "source": "panewslab",
            "kind": 2,
            "language": "zh-CN"
        },
        {
            "id": "z9ta7fcd",
            "title": "Parataxis Holdings拟通过约1829万美元的收购交易在韩国推出比特币财务平台",
            "description": "PANews 6月20日消息，据美通社报道，专注于比特币的投资初创公司Parataxis Holdings宣布已与Bridge Biotherapeutics, Inc.达成最终协议，将投资250亿韩元（约1829万美元），使Parataxis Holdings获得该公司的控股权，以收购韩国Bridge Biotherapeutics，旨在在韩国公开市场推出机构支持的比特币财务平台。此次交易将在韩国公开市场创建一个基于比特币的原生资金管理平台，该平台由在数字资产投资方面拥有丰富经验的机构投资者提供支持。\r\n此前消息，Parataxis Holdings计划通过SPAC交易上市，交易尚需完成尽职调查、签署最终协议及获得监管批准等常规程序。",
            "link": "https://www.panewslab.com/zh/sqarticledetails/z9ta7fcd.html",
            "pub_date": "2025-06-20 20:21:30",
            "source": "panewslab",
            "kind": 2,
            "language": "zh-CN"
        },
        {
            "id": "x364v7ie",
            "title": "Access Protocol提醒：创建者ElogisoX帐户被黑，请保持警惕",
            "description": "PANews 6月20日消息，Access Protocol在X平台发布提醒称，其创建者Elogiso（@elogiso）的X帐户最近遭到黑客攻击，诈骗者可能会通过包含恶意链接的虚假合作请求（例如播客采访）与用户联系。如果有人收到任何可疑消息，请立即向官方发送私信进行核实，保持警惕。",
            "link": "https://www.panewslab.com/zh/sqarticledetails/x364v7ie.html",
            "pub_date": "2025-06-20 20:11:33",
            "source": "panewslab",
            "kind": 2,
            "language": "zh-CN"
        },
        {
            "id": "k0xo1195",
            "title": "Gate Wallet BountyDrop新上线TCOM空投活动",
            "description": "PANews 6月20日消息，据官方活动页面，Gate Wallet BountyDrop 今日已上线 TCOM 空投活动，用户可通过 Gate Wallet App“发现”页面进入 BountyDrop 模块参与任务，完成指定操作即有机会赢取奖励。\r\nBountyDrop 是 Gate Wallet 发现页中的专属赚币活动专区，用户通过完成简单任务，即有机会赢取奖励或参与抽签获取空投代币。\r\n近期，Gate Wallet 已上线重要行情页功能，引入了更丰富的链上关键指标，聪明钱信号金币/银币/铜币等，辅助用户做出更快速准确的交易决策。\r\nGate Wallet 是行业领先的多链加密钱包，一站式连接 100+ 公链、数百万资产与上万个 DApp，开启专业级 Web3 体验，为每一个 Web3 需求提供最优解。",
            "link": "https://www.panewslab.com/zh/sqarticledetails/k0xo1195.html",
            "pub_date": "2025-06-20 20:02:46",
            "source": "panewslab",
            "kind": 2,
            "language": "zh-CN"
        }
    ]
}