{
    "data": [
        {
            "title": "菲律宾官员：我们不能对食糖和大米实行零关税。",
            "id": 1101145,
            "description": "",
            "link": "https://www.fx168news.com/express/fastnews/1101145",
            "pub_date": "2025-07-25 15:33:03",
            "source": "fx168",
            "kind": 2,
            "language": "zh-CN"
        },
        {
            "title": "韩国3年期公司债收益率上升1个基点至2.974%。",
            "id": 1101146,
            "description": "",
            "link": "https://www.fx168news.com/express/fastnews/1101146",
            "pub_date": "2025-07-25 15:33:03",
            "source": "fx168",
            "kind": 2,
            "language": "zh-CN"
        },
        {
            "title": "近期，多名来普吉岛的中国公民因拿错旧护照或不小心致使护照污损，被泰国移民部门拒绝入境并罚款，另有数十名游客在普吉、攀牙、甲米旅行时不慎遗失或浸泡护照，给自己的行程造成极大不便。驻普吉领事办公室再次提醒中国游客，中华人民共和国护照是中国公民出入国境和在国外证明国籍和身份的证件，务必妥善保管。根据泰国移民局规定，没有护照或护照失效、有损，将被拒绝入境、罚款并遣返。",
            "id": 1101147,
            "description": "",
            "link": "https://www.fx168news.com/express/fastnews/1101147",
            "pub_date": "2025-07-25 15:34:02",
            "source": "fx168",
            "kind": 2,
            "language": "zh-CN"
        },
        {
            "title": "比利时电信公司Proximus股价延续跌势，目前下跌12.5%，有望创下自2020年3月底以来表现最糟糕的一天。",
            "id": 1101148,
            "description": "",
            "link": "https://www.fx168news.com/express/fastnews/1101148",
            "pub_date": "2025-07-25 15:35:03",
            "source": "fx168",
            "kind": 2,
            "language": "zh-CN"
        },
        {
            "title": "欧洲股市下跌，汽车股拖累，投资者关注美欧贸易谈判",
            "id": 1101149,
            "description": "",
            "link": "https://www.fx168news.com/express/fastnews/1101149",
            "pub_date": "2025-07-25 15:35:09",
            "source": "fx168",
            "kind": 2,
            "language": "zh-CN"
        },
        {
            "title": "俄罗斯联邦反垄断局7月25日对俄罗斯天然气工业股份公司（俄气）旗下公司提起调查，指控其减少交易所的燃料销售量，称该行为涉嫌违反反垄断法律，公司应保持在交易所交易中燃料销售的规律性和均衡性。",
            "id": 1101130,
            "description": "",
            "link": "https://www.fx168news.com/express/fastnews/1101130",
            "pub_date": "2025-07-25 15:28:02",
            "source": "fx168",
            "kind": 2,
            "language": "zh-CN"
        },
        {
            "title": "LG电子计划提升美国和墨西哥工厂的产能。",
            "id": 1101131,
            "description": "",
            "link": "https://www.fx168news.com/express/fastnews/1101131",
            "pub_date": "2025-07-25 15:28:11",
            "source": "fx168",
            "kind": 2,
            "language": "zh-CN"
        },
        {
            "title": "土耳其财长：预计中期内通胀率将保持在2%的水平。",
            "id": 1101132,
            "description": "",
            "link": "https://www.fx168news.com/express/fastnews/1101132",
            "pub_date": "2025-07-25 15:29:02",
            "source": "fx168",
            "kind": 2,
            "language": "zh-CN"
        },
        {
            "title": "德国商业银行、加拿大皇家银行下调对欧洲央行最终降息的预期。",
            "id": 1101133,
            "description": "",
            "link": "https://www.fx168news.com/express/fastnews/1101133",
            "pub_date": "2025-07-25 15:30:03",
            "source": "fx168",
            "kind": 2,
            "language": "zh-CN"
        },
        {
            "title": "LG电子：由于关税问题，下半年美国家电市场前景不容乐观。",
            "id": 1101134,
            "description": "",
            "link": "https://www.fx168news.com/express/fastnews/1101134",
            "pub_date": "2025-07-25 15:30:03",
            "source": "fx168",
            "kind": 2,
            "language": "zh-CN"
        }
    ]
}